Workbook

Sheet Expenses
A1: Date | B1: Vendor | C1: Description | D1: Category | E1: Amount (ex VAT) | F1: VAT (20%) | G1: Total (inc VAT) | H1: Currency | I1: Receipt Ref | J1: Payment Method | K1: Notes
A2: 46101 | B2: 1st Formations | C2: Company formation - Paybacker LTD (Order 5790040) | D2: Professional Services | E2: TBC | F2: TBC | G2: TBC | H2: GBP | I2: 5790040 | J2: Card | K2: Amount in attached invoice - check PDF
A3: 46103 | B3: 123 Reg | C3: .AI Domain Registration - paybacker.ai (2 years) | D3: Software & SaaS | E3: 155.98 | F3: 31.2 | G3: 187.18 | H3: GBP | I3: 4043764096 | J3: Card
A4: 46103 | B4: Vercel | C4: Pro plan (Mar 22 - Apr 21, 2026) | D4: Hosting & Infrastructure | E4: 20 | F4: 0 | G4: 20 | H4: USD | I4: 2633-3613 | J4: Mastercard 4679 | K4: No VAT charged
A5: 46104 | B5: Anthropic | C5: Claude API credits | D5: Software & SaaS | E5: 11 | F5: 2.2 | G5: 13.2 | H5: USD | I5: 2288-3920-9674 | J5: Link | K5: Invoice 6IO6ZR0S-0054
A6: 46104 | B6: Railway | C6: Hobby plan (Mar 23 - Apr 23, 2026) | D6: Hosting & Infrastructure | E6: 5 | F6: 0 | G6: 5 | H6: USD | I6: 2638-8141 | J6: Mastercard 1730 | K6: No VAT charged
A7: 46105 | B7: Anthropic | C7: Claude API credits | D7: Software & SaaS | E7: 22 | F7: 4.4 | G7: 26.4 | H7: USD | I7: 2721-7395-8885 | J7: Link | K7: Invoice 6IO6ZR0S-0055
A8: 46105 | B8: Anthropic | C8: Claude API credits | D8: Software & SaaS | E8: 12 | F8: 2.4 | G8: 14.4 | H8: USD | I8: 2972-6108-0950 | J8: Link | K8: Invoice 6IO6ZR0S-0056
A9: 46105 | B9: Anthropic | C9: Claude API credits | D9: Software & SaaS | E9: 10 | F9: 2 | G9: 12 | H9: USD | I9: 2114-3091-3118 | J9: Link | K9: Invoice 6IO6ZR0S-0057
A10: 46105 | B10: Anthropic | C10: Claude API credits | D10: Software & SaaS | E10: 12 | F10: 2.4 | G10: 14.4 | H10: USD | I10: 2497-4394-3354 | J10: Link | K10: Invoice 6IO6ZR0S-0058
A11: 46105 | B11: Google Ads | C11: Advertising spend | D11: Advertising | E11: 16.67 | F11: 3.33 | G11: 20 | H11: GBP | I11: 317-010-5897 | J11: Card | K11: Payment received confirmation
A12: 46105 | B12: Google Ads | C12: Advertising spend | D12: Advertising | E12: 16.67 | F12: 3.33 | G12: 20 | H12: GBP | I12: 317-010-5897-2 | J12: Card | K12: Second payment same day
A13: 46105 | B13: Google Cloud | C13: Cloud Platform & APIs | D13: Hosting & Infrastructure | E13: 16.67 | F13: 3.33 | G13: 20 | H13: GBP | I13: 01216F-808B2E-0913F6 | J13: Visa 3001
A14: 46105 | B14: Google Workspace | C14: Business email (paybacker.co.uk) | D14: Software & SaaS | E14: 33.33 | F14: 6.67 | G14: 40 | H14: GBP | I14: paybacker.co.uk | J14: Card
A15: 46106 | B15: Anthropic | C15: Claude API credits | D15: Software & SaaS | E15: 25 | F15: 5 | G15: 30 | H15: USD | I15: 2306-0387-6306 | J15: Link | K15: Invoice 6IO6ZR0S-0059
A16: 46107 | B16: ElevenLabs | C16: Creator subscription (Mar 26 - Apr 26) | D16: Software & SaaS | E16: 11 | F16: 2.2 | G16: 13.2 | H16: USD | I16: 2739-7909-4965 | J16: Mastercard 0355 | K16: 50% first month discount applied
A17: 46108 | B17: ICO | C17: Data Protection Fee - Direct Debit setup | D17: Professional Services | E17: TBC | F17: TBC | G17: TBC | H17: GBP | I17: ZC111084 | J17: Direct Debit | K17: DD setup confirmation - annual fee ~£40
A18: 46109 | B18: Anthropic | C18: Claude API credits | D18: Software & SaaS | E18: 20 | F18: 4 | G18: 24 | H18: USD | I18: 2379-1573-1698 | J18: Link | K18: Invoice 6IO6ZR0S-0060
A19: 46112 | B19: Anthropic | C19: Claude API credits | D19: Software & SaaS | E19: 20 | F19: 4 | G19: 24 | H19: USD | I19: 2300-6108-8898 | J19: Link | K19: Invoice 6IO6ZR0S-0061
A20: 46113 | B20: Awin | C20: Affiliate network invoice | D20: Advertising | E20: TBC | F20: TBC | G20: TBC | H20: GBP | I20: 1241-436122 | J20: Direct Debit | K20: Amount in attached PDF invoice
A21: 46114 | B21: Google Ads | C21: Monthly billing document | D21: Advertising | E21: TBC | F21: TBC | G21: TBC | H21: GBP | I21: 5534845723 | J21: Card | K21: Invoice ready - check Google Ads dashboard
A22: 46115 | B22: Anthropic | C22: Claude API credits | D22: Software & SaaS | E22: 10 | F22: 2 | G22: 12 | H22: USD | I22: 2353-7134-2101 | J22: Link | K22: Invoice 6IO6ZR0S-0062
A23: 46115 | B23: Obsidian | C23: Sync yearly subscription (Standard 1GB) | D23: Software & SaaS | E23: 48 | F23: 0 | G23: 48 | H23: USD | I23: 1077-9581 | J23: Mastercard 0355 | K23: Annual - no VAT charged
A24: 46116 | B24: Anthropic | C24: Claude API credits | D24: Software & SaaS | E24: 6 | F24: 1.2 | G24: 7.2 | H24: USD | I24: 2022-5502-6712 | J24: Link | K24: Invoice 6IO6ZR0S-0063
A25: 46117 | B25: Anthropic | C25: Claude API credits | D25: Software & SaaS | E25: 8 | F25: 1.6 | G25: 9.6 | H25: USD | I25: 2522-0819-0428 | J25: Link | K25: Invoice 6IO6ZR0S-0064
A26: 46117 | B26: Render | C26: Servers + Disks hosting | D26: Hosting & Infrastructure | E26: 10.66 | F26: 0 | G26: 10.66 | H26: USD | I26: 2328-6691 | J26: Mastercard 9384 | K26: No VAT charged
A27: 46117 | B27: TAC Security | C27: ESOF AppSec ADA CASA - Basic (Google Play compliance) | D27: Software & SaaS | E27: 540 | F27: 0 | G27: 540 | H27: USD | I27: TAC-7425 | J27: Card | K27: Google Play Store security compliance - no VAT charged
A28: 46118 | B28: Anthropic | C28: Claude API credits (one-time purchase) | D28: Software & SaaS | E28: 10 | F28: 2 | G28: 12 | H28: USD | I28: 2444-5361-4827 | J28: Link | K28: Invoice 6IO6ZR0S-0066
A29: 46118 | B29: Google | C29: Google Play Developer Registration Fee | D29: Software & SaaS | E29: 25 | F29: 0 | G29: 25 | H29: USD | I29: PDS.3479-5651-0346-04283 | J29: Mastercard 0355 | K29: One-time fee - no VAT charged
A30: 46118 | B30: Anthropic | C30: Claude API credits (auto recharge) | D30: Software & SaaS | E30: 10.17 | F30: 2.03 | G30: 12.2 | H30: GBP | I30: 2548-7798-7819 | J30: Link | K30: Invoice RRQJD1BI-0007
A31: 46118 | B31: Anthropic | C31: Claude API credits (prepaid extra usage) | D31: Software & SaaS | E31: 33.75 | F31: 6.75 | G31: 40.5 | H31: GBP | I31: 2499-0601-0904 | J31: Link | K31: Invoice RRQJD1BI-0006
A32: 46118 | B32: Anthropic | C32: Claude API credits (auto recharge) | D32: Software & SaaS | E32: 14.46 | F32: 2.89 | G32: 17.35 | H32: GBP | I32: 2546-2529-5668 | J32: Link | K32: Invoice RRQJD1BI-0009
A33: 46118 | B33: Anthropic | C33: Claude API credits (auto recharge) | D33: Software & SaaS | E33: 10.9 | F33: 2.18 | G33: 13.08 | H33: GBP | I33: 2196-6364-5858 | J33: Link | K33: Invoice RRQJD1BI-0010
... A51: 46123 | B51: Anthropic | C51: Claude API credits (one-time credit purchase) | D51: Software & SaaS | E51: 20 | F51: 4 | G51: 24 | H51: USD | I51: 2229-7505-8193 | J51: Link | K51: Invoice 6IO6ZR0S-0069
D52: TOTALS (numeric entries only): | E52: =SUM(E2:E51) -> 1575.77 | F52: =SUM(F2:F51) -> 156.61 | G52: =SUM(G2:G51) -> 1732.38

Sheet Summary
A1: Paybacker Business Expenses Summary 2026
A3: Monthly Totals by Category
A4: Category | B4: Jan | C4: Feb | D4: Mar | E4: Apr | F4: May | G4: Jun | H4: Jul | I4: Aug | J4: Sep | K4: Oct | L4: Nov | M4: Dec | N4: Annual Total
A5: Software & SaaS | B5: =SUMPRODUCT((IF(ISNUMBER(Expenses!$G$2:$G$100),Expenses!$G$2:$G$100,0))*(IF(ISNUMBER(Expenses!$A$2:$A$100),MONTH(Expenses!$A$2:$A$100),13)=1)*(Expenses!$D$2:$D$100="Software & SaaS")) -> 0 | C5: =SUMPRODUCT((IF(ISNUMBER(Expenses!$G$2:$G$100),Expenses!$G$2:$G$100,0))*(IF(ISNUMBER(Expenses!$A$2:$A$100),MONTH(Expenses!$A$2:$A$100),13)=2)*(Expenses!$D$2:$D$100="Software & SaaS")) -> 0 | D5: =SUMPRODUCT((IF(ISNUMBER(Expenses!$G$2:$G$100),Expenses!$G$2:$G$100,0))*(IF(ISNUMBER(Expenses!$A$2:$A$100),MONTH(Expenses!$A$2:$A$100),13)=3)*(Expenses!$D$2:$D$100="Software & SaaS")) -> 398.78 | E5: =SUMPRODUCT((IF(ISNUMBER(Expenses!$G$2:$G$100),Expenses!$G$2:$G$100,0))*(IF(ISNUMBER(Expenses!$A$2:$A$100),MONTH(Expenses!$A$2:$A$100),13)=4)*(Expenses!$D$2:$D$100="Software & SaaS")) -> 1237.94 | F5: =SUMPRODUCT((IF(ISNUMBER(Expenses!$G$2:$G$100),Expenses!$G$2:$G$100,0))*(IF(ISNUMBER(Expenses!$A$2:$A$100),MONTH(Expenses!$A$2:$A$100),13)=5)*(Expenses!$D$2:$D$100="Software & SaaS")) -> 0 | G5: =SUMPRODUCT((IF(ISNUMBER(Expenses!$G$2:$G$100),Expenses!$G$2:$G$100,0))*(IF(ISNUMBER(Expenses!$A$2:$A$100),MONTH(Expenses!$A$2:$A$100),13)=6)*(Expenses!$D$2:$D$100="Software & SaaS")) -> 0 | H5: =SUMPRODUCT((IF(ISNUMBER(Expenses!$G$2:$G$100),Expenses!$G$2:$G$100,0))*(IF(ISNUMBER(Expenses!$A$2:$A$100),MONTH(Expenses!$A$2:$A$100),13)=7)*(Expenses!$D$2:$D$100="Software & SaaS")) -> 0 | I5: =SUMPRODUCT((IF(ISNUMBER(Expenses!$G$2:$G$100),Expenses!$G$2:$G$100,0))*(IF(ISNUMBER(Expenses!$A$2:$A$100),MONTH(Expenses!$A$2:$A$100),13)=8)*(Expenses!$D$2:$D$100="Software & SaaS")) -> 0 | J5: =SUMPRODUCT((IF(ISNUMBER(Expenses!$G$2:$G$100),Expenses!$G$2:$G$100,0))*(IF(ISNUMBER(Expenses!$A$2:$A$100),MONTH(Expenses!$A$2:$A$100),13)=9)*(Expenses!$D$2:$D$100="Software & SaaS")) -> 0 | K5: =SUMPRODUCT((IF(ISNUMBER(Expenses!$G$2:$G$100),Expenses!$G$2:$G$100,0))*(IF(ISNUMBER(Expenses!$A$2:$A$100),MONTH(Expenses!$A$2:$A$100),13)=10)*(Expenses!$D$2:$D$100="Software & SaaS")) -> 0 | L5: =SUMPRODUCT((IF(ISNUMBER(Expenses!$G$2:$G$100),Expenses!$G$2:$G$100,0))*(IF(ISNUMBER(Expenses!$A$2:$A$100),MONTH(Expenses!$A$2:$A$100),13)=11)*(Expenses!$D$2:$D$100="Software & SaaS")) -> 0 | M5: =SUMPRODUCT((IF(ISNUMBER(Expenses!$G$2:$G$100),Expenses!$G$2:$G$100,0))*(IF(ISNUMBER(Expenses!$A$2:$A$100),MONTH(Expenses!$A$2:$A$100),13)=12)*(Expenses!$D$2:$D$100="Software & SaaS")) -> 0 | N5: =SUM(B5:M5) -> 1636.72
A6: Advertising | B6: =SUMPRODUCT((IF(ISNUMBER(Expenses!$G$2:$G$100),Expenses!$G$2:$G$100,0))*(IF(ISNUMBER(Expenses!$A$2:$A$100),MONTH(Expenses!$A$2:$A$100),13)=1)*(Expenses!$D$2:$D$100="Advertising")) -> 0 | C6: =SUMPRODUCT((IF(ISNUMBER(Expenses!$G$2:$G$100),Expenses!$G$2:$G$100,0))*(IF(ISNUMBER(Expenses!$A$2:$A$100),MONTH(Expenses!$A$2:$A$100),13)=2)*(Expenses!$D$2:$D$100="Advertising")) -> 0 | D6: =SUMPRODUCT((IF(ISNUMBER(Expenses!$G$2:$G$100),Expenses!$G$2:$G$100,0))*(IF(ISNUMBER(Expenses!$A$2:$A$100),MONTH(Expenses!$A$2:$A$100),13)=3)*(Expenses!$D$2:$D$100="Advertising")) -> 40 | E6: =SUMPRODUCT((IF(ISNUMBER(Expenses!$G$2:$G$100),Expenses!$G$2:$G$100,0))*(IF(ISNUMBER(Expenses!$A$2:$A$100),MONTH(Expenses!$A$2:$A$100),13)=4)*(Expenses!$D$2:$D$100="Advertising")) -> 0 | F6: =SUMPRODUCT((IF(ISNUMBER(Expenses!$G$2:$G$100),Expenses!$G$2:$G$100,0))*(IF(ISNUMBER(Expenses!$A$2:$A$100),MONTH(Expenses!$A$2:$A$100),13)=5)*(Expenses!$D$2:$D$100="Advertising")) -> 0 | G6: =SUMPRODUCT((IF(ISNUMBER(Expenses!$G$2:$G$100),Expenses!$G$2:$G$100,0))*(IF(ISNUMBER(Expenses!$A$2:$A$100),MONTH(Expenses!$A$2:$A$100),13)=6)*(Expenses!$D$2:$D$100="Advertising")) -> 0 | H6: =SUMPRODUCT((IF(ISNUMBER(Expenses!$G$2:$G$100),Expenses!$G$2:$G$100,0))*(IF(ISNUMBER(Expenses!$A$2:$A$100),MONTH(Expenses!$A$2:$A$100),13)=7)*(Expenses!$D$2:$D$100="Advertising")) -> 0 | I6: =SUMPRODUCT((IF(ISNUMBER(Expenses!$G$2:$G$100),Expenses!$G$2:$G$100,0))*(IF(ISNUMBER(Expenses!$A$2:$A$100),MONTH(Expenses!$A$2:$A$100),13)=8)*(Expenses!$D$2:$D$100="Advertising")) -> 0 | J6: =SUMPRODUCT((IF(ISNUMBER(Expenses!$G$2:$G$100),Expenses!$G$2:$G$100,0))*(IF(ISNUMBER(Expenses!$A$2:$A$100),MONTH(Expenses!$A$2:$A$100),13)=9)*(Expenses!$D$2:$D$100="Advertising")) -> 0 | K6: =SUMPRODUCT((IF(ISNUMBER(Expenses!$G$2:$G$100),Expenses!$G$2:$G$100,0))*(IF(ISNUMBER(Expenses!$A$2:$A$100),MONTH(Expenses!$A$2:$A$100),13)=10)*(Expenses!$D$2:$D$100="Advertising")) -> 0 | L6: =SUMPRODUCT((IF(ISNUMBER(Expenses!$G$2:$G$100),Expenses!$G$2:$G$100,0))*(IF(ISNUMBER(Expenses!$A$2:$A$100),MONTH(Expenses!$A$2:$A$100),13)=11)*(Expenses!$D$2:$D$100="Advertising")) -> 0 | M6: =SUMPRODUCT((IF(ISNUMBER(Expenses!$G$2:$G$100),Expenses!$G$2:$G$100,0))*(IF(ISNUMBER(Expenses!$A$2:$A$100),MONTH(Expenses!$A$2:$A$100),13)=12)*(Expenses!$D$2:$D$100="Advertising")) -> 0 | N6: =SUM(B6:M6) -> 40
A7: Hosting & Infrastructure | B7: =SUMPRODUCT((IF(ISNUMBER(Expenses!$G$2:$G$100),Expenses!$G$2:$G$100,0))*(IF(ISNUMBER(Expenses!$A$2:$A$100),MONTH(Expenses!$A$2:$A$100),13)=1)*(Expenses!$D$2:$D$100="Hosting & Infrastructure")) -> 0 | C7: =SUMPRODUCT((IF(ISNUMBER(Expenses!$G$2:$G$100),Expenses!$G$2:$G$100,0))*(IF(ISNUMBER(Expenses!$A$2:$A$100),MONTH(Expenses!$A$2:$A$100),13)=2)*(Expenses!$D$2:$D$100="Hosting & Infrastructure")) -> 0 | D7: =SUMPRODUCT((IF(ISNUMBER(Expenses!$G$2:$G$100),Expenses!$G$2:$G$100,0))*(IF(ISNUMBER(Expenses!$A$2:$A$100),MONTH(Expenses!$A$2:$A$100),13)=3)*(Expenses!$D$2:$D$100="Hosting & Infrastructure")) -> 45 | E7: =SUMPRODUCT((IF(ISNUMBER(Expenses!$G$2:$G$100),Expenses!$G$2:$G$100,0))*(IF(ISNUMBER(Expenses!$A$2:$A$100),MONTH(Expenses!$A$2:$A$100),13)=4)*(Expenses!$D$2:$D$100="Hosting & Infrastructure")) -> 10.66 | F7: =SUMPRODUCT((IF(ISNUMBER(Expenses!$G$2:$G$100),Expenses!$G$2:$G$100,0))*(IF(ISNUMBER(Expenses!$A$2:$A$100),MONTH(Expenses!$A$2:$A$100),13)=5)*(Expenses!$D$2:$D$100="Hosting & Infrastructure")) -> 0 | G7: =SUMPRODUCT((IF(ISNUMBER(Expenses!$G$2:$G$100),Expenses!$G$2:$G$100,0))*(IF(ISNUMBER(Expenses!$A$2:$A$100),MONTH(Expenses!$A$2:$A$100),13)=6)*(Expenses!$D$2:$D$100="Hosting & Infrastructure")) -> 0 | H7: =SUMPRODUCT((IF(ISNUMBER(Expenses!$G$2:$G$100),Expenses!$G$2:$G$100,0))*(IF(ISNUMBER(Expenses!$A$2:$A$100),MONTH(Expenses!$A$2:$A$100),13)=7)*(Expenses!$D$2:$D$100="Hosting & Infrastructure")) -> 0 | I7: =SUMPRODUCT((IF(ISNUMBER(Expenses!$G$2:$G$100),Expenses!$G$2:$G$100,0))*(IF(ISNUMBER(Expenses!$A$2:$A$100),MONTH(Expenses!$A$2:$A$100),13)=8)*(Expenses!$D$2:$D$100="Hosting & Infrastructure")) -> 0 | J7: =SUMPRODUCT((IF(ISNUMBER(Expenses!$G$2:$G$100),Expenses!$G$2:$G$100,0))*(IF(ISNUMBER(Expenses!$A$2:$A$100),MONTH(Expenses!$A$2:$A$100),13)=9)*(Expenses!$D$2:$D$100="Hosting & Infrastructure")) -> 0 | K7: =SUMPRODUCT((IF(ISNUMBER(Expenses!$G$2:$G$100),Expenses!$G$2:$G$100,0))*(IF(ISNUMBER(Expenses!$A$2:$A$100),MONTH(Expenses!$A$2:$A$100),13)=10)*(Expenses!$D$2:$D$100="Hosting & Infrastructure")) -> 0 | L7: =SUMPRODUCT((IF(ISNUMBER(Expenses!$G$2:$G$100),Expenses!$G$2:$G$100,0))*(IF(ISNUMBER(Expenses!$A$2:$A$100),MONTH(Expenses!$A$2:$A$100),13)=11)*(Expenses!$D$2:$D$100="Hosting & Infrastructure")) -> 0 | M7: =SUMPRODUCT((IF(ISNUMBER(Expenses!$G$2:$G$100),Expenses!$G$2:$G$100,0))*(IF(ISNUMBER(Expenses!$A$2:$A$100),MONTH(Expenses!$A$2:$A$100),13)=12)*(Expenses!$D$2:$D$100="Hosting & Infrastructure")) -> 0 | N7: =SUM(B7:M7) -> 55.66
A8: Professional Services | B8: =SUMPRODUCT((IF(ISNUMBER(Expenses!$G$2:$G$100),Expenses!$G$2:$G$100,0))*(IF(ISNUMBER(Expenses!$A$2:$A$100),MONTH(Expenses!$A$2:$A$100),13)=1)*(Expenses!$D$2:$D$100="Professional Services")) -> 0 | C8: =SUMPRODUCT((IF(ISNUMBER(Expenses!$G$2:$G$100),Expenses!$G$2:$G$100,0))*(IF(ISNUMBER(Expenses!$A$2:$A$100),MONTH(Expenses!$A$2:$A$100),13)=2)*(Expenses!$D$2:$D$100="Professional Services")) -> 0 | D8: =SUMPRODUCT((IF(ISNUMBER(Expenses!$G$2:$G$100),Expenses!$G$2:$G$100,0))*(IF(ISNUMBER(Expenses!$A$2:$A$100),MONTH(Expenses!$A$2:$A$100),13)=3)*(Expenses!$D$2:$D$100="Professional Services")) -> 0 | E8: =SUMPRODUCT((IF(ISNUMBER(Expenses!$G$2:$G$100),Expenses!$G$2:$G$100,0))*(IF(ISNUMBER(Expenses!$A$2:$A$100),MONTH(Expenses!$A$2:$A$100),13)=4)*(Expenses!$D$2:$D$100="Professional Services")) -> 0 | F8: =SUMPRODUCT((IF(ISNUMBER(Expenses!$G$2:$G$100),Expenses!$G$2:$G$100,0))*(IF(ISNUMBER(Expenses!$A$2:$A$100),MONTH(Expenses!$A$2:$A$100),13)=5)*(Expenses!$D$2:$D$100="Professional Services")) -> 0 | G8: =SUMPRODUCT((IF(ISNUMBER(Expenses!$G$2:$G$100),Expenses!$G$2:$G$100,0))*(IF(ISNUMBER(Expenses!$A$2:$A$100),MONTH(Expenses!$A$2:$A$100),13)=6)*(Expenses!$D$2:$D$100="Professional Services")) -> 0 | H8: =SUMPRODUCT((IF(ISNUMBER(Expenses!$G$2:$G$100),Expenses!$G$2:$G$100,0))*(IF(ISNUMBER(Expenses!$A$2:$A$100),MONTH(Expenses!$A$2:$A$100),13)=7)*(Expenses!$D$2:$D$100="Professional Services")) -> 0 | I8: =SUMPRODUCT((IF(ISNUMBER(Expenses!$G$2:$G$100),Expenses!$G$2:$G$100,0))*(IF(ISNUMBER(Expenses!$A$2:$A$100),MONTH(Expenses!$A$2:$A$100),13)=8)*(Expenses!$D$2:$D$100="Professional Services")) -> 0 | J8: =SUMPRODUCT((IF(ISNUMBER(Expenses!$G$2:$G$100),Expenses!$G$2:$G$100,0))*(IF(ISNUMBER(Expenses!$A$2:$A$100),MONTH(Expenses!$A$2:$A$100),13)=9)*(Expenses!$D$2:$D$100="Professional Services")) -> 0 | K8: =SUMPRODUCT((IF(ISNUMBER(Expenses!$G$2:$G$100),Expenses!$G$2:$G$100,0))*(IF(ISNUMBER(Expenses!$A$2:$A$100),MONTH(Expenses!$A$2:$A$100),13)=10)*(Expenses!$D$2:$D$100="Professional Services")) -> 0 | L8: =SUMPRODUCT((IF(ISNUMBER(Expenses!$G$2:$G$100),Expenses!$G$2:$G$100,0))*(IF(ISNUMBER(Expenses!$A$2:$A$100),MONTH(Expenses!$A$2:$A$100),13)=11)*(Expenses!$D$2:$D$100="Professional Services")) -> 0 | M8: =SUMPRODUCT((IF(ISNUMBER(Expenses!$G$2:$G$100),Expenses!$G$2:$G$100,0))*(IF(ISNUMBER(Expenses!$A$2:$A$100),MONTH(Expenses!$A$2:$A$100),13)=12)*(Expenses!$D$2:$D$100="Professional Services")) -> 0 | N8: =SUM(B8:M8) -> 0
A9: Office & Equipment | B9: =SUMPRODUCT((IF(ISNUMBER(Expenses!$G$2:$G$100),Expenses!$G$2:$G$100,0))*(IF(ISNUMBER(Expenses!$A$2:$A$100),MONTH(Expenses!$A$2:$A$100),13)=1)*(Expenses!$D$2:$D$100="Office & Equipment")) -> 0 | C9: =SUMPRODUCT((IF(ISNUMBER(Expenses!$G$2:$G$100),Expenses!$G$2:$G$100,0))*(IF(ISNUMBER(Expenses!$A$2:$A$100),MONTH(Expenses!$A$2:$A$100),13)=2)*(Expenses!$D$2:$D$100="Office & Equipment")) -> 0 | D9: =SUMPRODUCT((IF(ISNUMBER(Expenses!$G$2:$G$100),Expenses!$G$2:$G$100,0))*(IF(ISNUMBER(Expenses!$A$2:$A$100),MONTH(Expenses!$A$2:$A$100),13)=3)*(Expenses!$D$2:$D$100="Office & Equipment")) -> 0 | E9: =SUMPRODUCT((IF(ISNUMBER(Expenses!$G$2:$G$100),Expenses!$G$2:$G$100,0))*(IF(ISNUMBER(Expenses!$A$2:$A$100),MONTH(Expenses!$A$2:$A$100),13)=4)*(Expenses!$D$2:$D$100="Office & Equipment")) -> 0 | F9: =SUMPRODUCT((IF(ISNUMBER(Expenses!$G$2:$G$100),Expenses!$G$2:$G$100,0))*(IF(ISNUMBER(Expenses!$A$2:$A$100),MONTH(Expenses!$A$2:$A$100),13)=5)*(Expenses!$D$2:$D$100="Office & Equipment")) -> 0 | G9: =SUMPRODUCT((IF(ISNUMBER(Expenses!$G$2:$G$100),Expenses!$G$2:$G$100,0))*(IF(ISNUMBER(Expenses!$A$2:$A$100),MONTH(Expenses!$A$2:$A$100),13)=6)*(Expenses!$D$2:$D$100="Office & Equipment")) -> 0 | H9: =SUMPRODUCT((IF(ISNUMBER(Expenses!$G$2:$G$100),Expenses!$G$2:$G$100,0))*(IF(ISNUMBER(Expenses!$A$2:$A$100),MONTH(Expenses!$A$2:$A$100),13)=7)*(Expenses!$D$2:$D$100="Office & Equipment")) -> 0 | I9: =SUMPRODUCT((IF(ISNUMBER(Expenses!$G$2:$G$100),Expenses!$G$2:$G$100,0))*(IF(ISNUMBER(Expenses!$A$2:$A$100),MONTH(Expenses!$A$2:$A$100),13)=8)*(Expenses!$D$2:$D$100="Office & Equipment")) -> 0 | J9: =SUMPRODUCT((IF(ISNUMBER(Expenses!$G$2:$G$100),Expenses!$G$2:$G$100,0))*(IF(ISNUMBER(Expenses!$A$2:$A$100),MONTH(Expenses!$A$2:$A$100),13)=9)*(Expenses!$D$2:$D$100="Office & Equipment")) -> 0 | K9: =SUMPRODUCT((IF(ISNUMBER(Expenses!$G$2:$G$100),Expenses!$G$2:$G$100,0))*(IF(ISNUMBER(Expenses!$A$2:$A$100),MONTH(Expenses!$A$2:$A$100),13)=10)*(Expenses!$D$2:$D$100="Office & Equipment")) -> 0 | L9: =SUMPRODUCT((IF(ISNUMBER(Expenses!$G$2:$G$100),Expenses!$G$2:$G$100,0))*(IF(ISNUMBER(Expenses!$A$2:$A$100),MONTH(Expenses!$A$2:$A$100),13)=11)*(Expenses!$D$2:$D$100="Office & Equipment")) -> 0 | M9: =SUMPRODUCT((IF(ISNUMBER(Expenses!$G$2:$G$100),Expenses!$G$2:$G$100,0))*(IF(ISNUMBER(Expenses!$A$2:$A$100),MONTH(Expenses!$A$2:$A$100),13)=12)*(Expenses!$D$2:$D$100="Office & Equipment")) -> 0 | N9: =SUM(B9:M9) -> 0
A10: Travel & Subsistence | B10: =SUMPRODUCT((IF(ISNUMBER(Expenses!$G$2:$G$100),Expenses!$G$2:$G$100,0))*(IF(ISNUMBER(Expenses!$A$2:$A$100),MONTH(Expenses!$A$2:$A$100),13)=1)*(Expenses!$D$2:$D$100="Travel & Subsistence")) -> 0 | C10: =SUMPRODUCT((IF(ISNUMBER(Expenses!$G$2:$G$100),Expenses!$G$2:$G$100,0))*(IF(ISNUMBER(Expenses!$A$2:$A$100),MONTH(Expenses!$A$2:$A$100),13)=2)*(Expenses!$D$2:$D$100="Travel & Subsistence")) -> 0 | D10: =SUMPRODUCT((IF(ISNUMBER(Expenses!$G$2:$G$100),Expenses!$G$2:$G$100,0))*(IF(ISNUMBER(Expenses!$A$2:$A$100),MONTH(Expenses!$A$2:$A$100),13)=3)*(Expenses!$D$2:$D$100="Travel & Subsistence")) -> 0 | E10: =SUMPRODUCT((IF(ISNUMBER(Expenses!$G$2:$G$100),Expenses!$G$2:$G$100,0))*(IF(ISNUMBER(Expenses!$A$2:$A$100),MONTH(Expenses!$A$2:$A$100),13)=4)*(Expenses!$D$2:$D$100="Travel & Subsistence")) -> 0 | F10: =SUMPRODUCT((IF(ISNUMBER(Expenses!$G$2:$G$100),Expenses!$G$2:$G$100,0))*(IF(ISNUMBER(Expenses!$A$2:$A$100),MONTH(Expenses!$A$2:$A$100),13)=5)*(Expenses!$D$2:$D$100="Travel & Subsistence")) -> 0 | G10: =SUMPRODUCT((IF(ISNUMBER(Expenses!$G$2:$G$100),Expenses!$G$2:$G$100,0))*(IF(ISNUMBER(Expenses!$A$2:$A$100),MONTH(Expenses!$A$2:$A$100),13)=6)*(Expenses!$D$2:$D$100="Travel & Subsistence")) -> 0 | H10: =SUMPRODUCT((IF(ISNUMBER(Expenses!$G$2:$G$100),Expenses!$G$2:$G$100,0))*(IF(ISNUMBER(Expenses!$A$2:$A$100),MONTH(Expenses!$A$2:$A$100),13)=7)*(Expenses!$D$2:$D$100="Travel & Subsistence")) -> 0 | I10: =SUMPRODUCT((IF(ISNUMBER(Expenses!$G$2:$G$100),Expenses!$G$2:$G$100,0))*(IF(ISNUMBER(Expenses!$A$2:$A$100),MONTH(Expenses!$A$2:$A$100),13)=8)*(Expenses!$D$2:$D$100="Travel & Subsistence")) -> 0 | J10: =SUMPRODUCT((IF(ISNUMBER(Expenses!$G$2:$G$100),Expenses!$G$2:$G$100,0))*(IF(ISNUMBER(Expenses!$A$2:$A$100),MONTH(Expenses!$A$2:$A$100),13)=9)*(Expenses!$D$2:$D$100="Travel & Subsistence")) -> 0 | K10: =SUMPRODUCT((IF(ISNUMBER(Expenses!$G$2:$G$100),Expenses!$G$2:$G$100,0))*(IF(ISNUMBER(Expenses!$A$2:$A$100),MONTH(Expenses!$A$2:$A$100),13)=10)*(Expenses!$D$2:$D$100="Travel & Subsistence")) -> 0 | L10: =SUMPRODUCT((IF(ISNUMBER(Expenses!$G$2:$G$100),Expenses!$G$2:$G$100,0))*(IF(ISNUMBER(Expenses!$A$2:$A$100),MONTH(Expenses!$A$2:$A$100),13)=11)*(Expenses!$D$2:$D$100="Travel & Subsistence")) -> 0 | M10: =SUMPRODUCT((IF(ISNUMBER(Expenses!$G$2:$G$100),Expenses!$G$2:$G$100,0))*(IF(ISNUMBER(Expenses!$A$2:$A$100),MONTH(Expenses!$A$2:$A$100),13)=12)*(Expenses!$D$2:$D$100="Travel & Subsistence")) -> 0 | N10: =SUM(B10:M10) -> 0
A11: Phone & Internet | B11: =SUMPRODUCT((IF(ISNUMBER(Expenses!$G$2:$G$100),Expenses!$G$2:$G$100,0))*(IF(ISNUMBER(Expenses!$A$2:$A$100),MONTH(Expenses!$A$2:$A$100),13)=1)*(Expenses!$D$2:$D$100="Phone & Internet")) -> 0 | C11: =SUMPRODUCT((IF(ISNUMBER(Expenses!$G$2:$G$100),Expenses!$G$2:$G$100,0))*(IF(ISNUMBER(Expenses!$A$2:$A$100),MONTH(Expenses!$A$2:$A$100),13)=2)*(Expenses!$D$2:$D$100="Phone & Internet")) -> 0 | D11: =SUMPRODUCT((IF(ISNUMBER(Expenses!$G$2:$G$100),Expenses!$G$2:$G$100,0))*(IF(ISNUMBER(Expenses!$A$2:$A$100),MONTH(Expenses!$A$2:$A$100),13)=3)*(Expenses!$D$2:$D$100="Phone & Internet")) -> 0 | E11: =SUMPRODUCT((IF(ISNUMBER(Expenses!$G$2:$G$100),Expenses!$G$2:$G$100,0))*(IF(ISNUMBER(Expenses!$A$2:$A$100),MONTH(Expenses!$A$2:$A$100),13)=4)*(Expenses!$D$2:$D$100="Phone & Internet")) -> 0 | F11: =SUMPRODUCT((IF(ISNUMBER(Expenses!$G$2:$G$100),Expenses!$G$2:$G$100,0))*(IF(ISNUMBER(Expenses!$A$2:$A$100),MONTH(Expenses!$A$2:$A$100),13)=5)*(Expenses!$D$2:$D$100="Phone & Internet")) -> 0 | G11: =SUMPRODUCT((IF(ISNUMBER(Expenses!$G$2:$G$100),Expenses!$G$2:$G$100,0))*(IF(ISNUMBER(Expenses!$A$2:$A$100),MONTH(Expenses!$A$2:$A$100),13)=6)*(Expenses!$D$2:$D$100="Phone & Internet")) -> 0 | H11: =SUMPRODUCT((IF(ISNUMBER(Expenses!$G$2:$G$100),Expenses!$G$2:$G$100,0))*(IF(ISNUMBER(Expenses!$A$2:$A$100),MONTH(Expenses!$A$2:$A$100),13)=7)*(Expenses!$D$2:$D$100="Phone & Internet")) -> 0 | I11: =SUMPRODUCT((IF(ISNUMBER(Expenses!$G$2:$G$100),Expenses!$G$2:$G$100,0))*(IF(ISNUMBER(Expenses!$A$2:$A$100),MONTH(Expenses!$A$2:$A$100),13)=8)*(Expenses!$D$2:$D$100="Phone & Internet")) -> 0 | J11: =SUMPRODUCT((IF(ISNUMBER(Expenses!$G$2:$G$100),Expenses!$G$2:$G$100,0))*(IF(ISNUMBER(Expenses!$A$2:$A$100),MONTH(Expenses!$A$2:$A$100),13)=9)*(Expenses!$D$2:$D$100="Phone & Internet")) -> 0 | K11: =SUMPRODUCT((IF(ISNUMBER(Expenses!$G$2:$G$100),Expenses!$G$2:$G$100,0))*(IF(ISNUMBER(Expenses!$A$2:$A$100),MONTH(Expenses!$A$2:$A$100),13)=10)*(Expenses!$D$2:$D$100="Phone & Internet")) -> 0 | L11: =SUMPRODUCT((IF(ISNUMBER(Expenses!$G$2:$G$100),Expenses!$G$2:$G$100,0))*(IF(ISNUMBER(Expenses!$A$2:$A$100),MONTH(Expenses!$A$2:$A$100),13)=11)*(Expenses!$D$2:$D$100="Phone & Internet")) -> 0 | M11: =SUMPRODUCT((IF(ISNUMBER(Expenses!$G$2:$G$100),Expenses!$G$2:$G$100,0))*(IF(ISNUMBER(Expenses!$A$2:$A$100),MONTH(Expenses!$A$2:$A$100),13)=12)*(Expenses!$D$2:$D$100="Phone & Internet")) -> 0 | N11: =SUM(B11:M11) -> 0
A12: Bank Charges | B12: =SUMPRODUCT((IF(ISNUMBER(Expenses!$G$2:$G$100),Expenses!$G$2:$G$100,0))*(IF(ISNUMBER(Expenses!$A$2:$A$100),MONTH(Expenses!$A$2:$A$100),13)=1)*(Expenses!$D$2:$D$100="Bank Charges")) -> 0 | C12: =SUMPRODUCT((IF(ISNUMBER(Expenses!$G$2:$G$100),Expenses!$G$2:$G$100,0))*(IF(ISNUMBER(Expenses!$A$2:$A$100),MONTH(Expenses!$A$2:$A$100),13)=2)*(Expenses!$D$2:$D$100="Bank Charges")) -> 0 | D12: =SUMPRODUCT((IF(ISNUMBER(Expenses!$G$2:$G$100),Expenses!$G$2:$G$100,0))*(IF(ISNUMBER(Expenses!$A$2:$A$100),MONTH(Expenses!$A$2:$A$100),13)=3)*(Expenses!$D$2:$D$100="Bank Charges")) -> 0 | E12: =SUMPRODUCT((IF(ISNUMBER(Expenses!$G$2:$G$100),Expenses!$G$2:$G$100,0))*(IF(ISNUMBER(Expenses!$A$2:$A$100),MONTH(Expenses!$A$2:$A$100),13)=4)*(Expenses!$D$2:$D$100="Bank Charges")) -> 0 | F12: =SUMPRODUCT((IF(ISNUMBER(Expenses!$G$2:$G$100),Expenses!$G$2:$G$100,0))*(IF(ISNUMBER(Expenses!$A$2:$A$100),MONTH(Expenses!$A$2:$A$100),13)=5)*(Expenses!$D$2:$D$100="Bank Charges")) -> 0 | G12: =SUMPRODUCT((IF(ISNUMBER(Expenses!$G$2:$G$100),Expenses!$G$2:$G$100,0))*(IF(ISNUMBER(Expenses!$A$2:$A$100),MONTH(Expenses!$A$2:$A$100),13)=6)*(Expenses!$D$2:$D$100="Bank Charges")) -> 0 | H12: =SUMPRODUCT((IF(ISNUMBER(Expenses!$G$2:$G$100),Expenses!$G$2:$G$100,0))*(IF(ISNUMBER(Expenses!$A$2:$A$100),MONTH(Expenses!$A$2:$A$100),13)=7)*(Expenses!$D$2:$D$100="Bank Charges")) -> 0 | I12: =SUMPRODUCT((IF(ISNUMBER(Expenses!$G$2:$G$100),Expenses!$G$2:$G$100,0))*(IF(ISNUMBER(Expenses!$A$2:$A$100),MONTH(Expenses!$A$2:$A$100),13)=8)*(Expenses!$D$2:$D$100="Bank Charges")) -> 0 | J12: =SUMPRODUCT((IF(ISNUMBER(Expenses!$G$2:$G$100),Expenses!$G$2:$G$100,0))*(IF(ISNUMBER(Expenses!$A$2:$A$100),MONTH(Expenses!$A$2:$A$100),13)=9)*(Expenses!$D$2:$D$100="Bank Charges")) -> 0 | K12: =SUMPRODUCT((IF(ISNUMBER(Expenses!$G$2:$G$100),Expenses!$G$2:$G$100,0))*(IF(ISNUMBER(Expenses!$A$2:$A$100),MONTH(Expenses!$A$2:$A$100),13)=10)*(Expenses!$D$2:$D$100="Bank Charges")) -> 0 | L12: =SUMPRODUCT((IF(ISNUMBER(Expenses!$G$2:$G$100),Expenses!$G$2:$G$100,0))*(IF(ISNUMBER(Expenses!$A$2:$A$100),MONTH(Expenses!$A$2:$A$100),13)=11)*(Expenses!$D$2:$D$100="Bank Charges")) -> 0 | M12: =SUMPRODUCT((IF(ISNUMBER(Expenses!$G$2:$G$100),Expenses!$G$2:$G$100,0))*(IF(ISNUMBER(Expenses!$A$2:$A$100),MONTH(Expenses!$A$2:$A$100),13)=12)*(Expenses!$D$2:$D$100="Bank Charges")) -> 0 | N12: =SUM(B12:M12) -> 0
A13: Insurance | B13: =SUMPRODUCT((IF(ISNUMBER(Expenses!$G$2:$G$100),Expenses!$G$2:$G$100,0))*(IF(ISNUMBER(Expenses!$A$2:$A$100),MONTH(Expenses!$A$2:$A$100),13)=1)*(Expenses!$D$2:$D$100="Insurance")) -> 0 | C13: =SUMPRODUCT((IF(ISNUMBER(Expenses!$G$2:$G$100),Expenses!$G$2:$G$100,0))*(IF(ISNUMBER(Expenses!$A$2:$A$100),MONTH(Expenses!$A$2:$A$100),13)=2)*(Expenses!$D$2:$D$100="Insurance")) -> 0 | D13: =SUMPRODUCT((IF(ISNUMBER(Expenses!$G$2:$G$100),Expenses!$G$2:$G$100,0))*(IF(ISNUMBER(Expenses!$A$2:$A$100),MONTH(Expenses!$A$2:$A$100),13)=3)*(Expenses!$D$2:$D$100="Insurance")) -> 0 | E13: =SUMPRODUCT((IF(ISNUMBER(Expenses!$G$2:$G$100),Expenses!$G$2:$G$100,0))*(IF(ISNUMBER(Expenses!$A$2:$A$100),MONTH(Expenses!$A$2:$A$100),13)=4)*(Expenses!$D$2:$D$100="Insurance")) -> 0 | F13: =SUMPRODUCT((IF(ISNUMBER(Expenses!$G$2:$G$100),Expenses!$G$2:$G$100,0))*(IF(ISNUMBER(Expenses!$A$2:$A$100),MONTH(Expenses!$A$2:$A$100),13)=5)*(Expenses!$D$2:$D$100="Insurance")) -> 0 | G13: =SUMPRODUCT((IF(ISNUMBER(Expenses!$G$2:$G$100),Expenses!$G$2:$G$100,0))*(IF(ISNUMBER(Expenses!$A$2:$A$100),MONTH(Expenses!$A$2:$A$100),13)=6)*(Expenses!$D$2:$D$100="Insurance")) -> 0 | H13: =SUMPRODUCT((IF(ISNUMBER(Expenses!$G$2:$G$100),Expenses!$G$2:$G$100,0))*(IF(ISNUMBER(Expenses!$A$2:$A$100),MONTH(Expenses!$A$2:$A$100),13)=7)*(Expenses!$D$2:$D$100="Insurance")) -> 0 | I13: =SUMPRODUCT((IF(ISNUMBER(Expenses!$G$2:$G$100),Expenses!$G$2:$G$100,0))*(IF(ISNUMBER(Expenses!$A$2:$A$100),MONTH(Expenses!$A$2:$A$100),13)=8)*(Expenses!$D$2:$D$100="Insurance")) -> 0 | J13: =SUMPRODUCT((IF(ISNUMBER(Expenses!$G$2:$G$100),Expenses!$G$2:$G$100,0))*(IF(ISNUMBER(Expenses!$A$2:$A$100),MONTH(Expenses!$A$2:$A$100),13)=9)*(Expenses!$D$2:$D$100="Insurance")) -> 0 | K13: =SUMPRODUCT((IF(ISNUMBER(Expenses!$G$2:$G$100),Expenses!$G$2:$G$100,0))*(IF(ISNUMBER(Expenses!$A$2:$A$100),MONTH(Expenses!$A$2:$A$100),13)=10)*(Expenses!$D$2:$D$100="Insurance")) -> 0 | L13: =SUMPRODUCT((IF(ISNUMBER(Expenses!$G$2:$G$100),Expenses!$G$2:$G$100,0))*(IF(ISNUMBER(Expenses!$A$2:$A$100),MONTH(Expenses!$A$2:$A$100),13)=11)*(Expenses!$D$2:$D$100="Insurance")) -> 0 | M13: =SUMPRODUCT((IF(ISNUMBER(Expenses!$G$2:$G$100),Expenses!$G$2:$G$100,0))*(IF(ISNUMBER(Expenses!$A$2:$A$100),MONTH(Expenses!$A$2:$A$100),13)=12)*(Expenses!$D$2:$D$100="Insurance")) -> 0 | N13: =SUM(B13:M13) -> 0
A14: Other | B14: =SUMPRODUCT((IF(ISNUMBER(Expenses!$G$2:$G$100),Expenses!$G$2:$G$100,0))*(IF(ISNUMBER(Expenses!$A$2:$A$100),MONTH(Expenses!$A$2:$A$100),13)=1)*(Expenses!$D$2:$D$100="Other")) -> 0 | C14: =SUMPRODUCT((IF(ISNUMBER(Expenses!$G$2:$G$100),Expenses!$G$2:$G$100,0))*(IF(ISNUMBER(Expenses!$A$2:$A$100),MONTH(Expenses!$A$2:$A$100),13)=2)*(Expenses!$D$2:$D$100="Other")) -> 0 | D14: =SUMPRODUCT((IF(ISNUMBER(Expenses!$G$2:$G$100),Expenses!$G$2:$G$100,0))*(IF(ISNUMBER(Expenses!$A$2:$A$100),MONTH(Expenses!$A$2:$A$100),13)=3)*(Expenses!$D$2:$D$100="Other")) -> 0 | E14: =SUMPRODUCT((IF(ISNUMBER(Expenses!$G$2:$G$100),Expenses!$G$2:$G$100,0))*(IF(ISNUMBER(Expenses!$A$2:$A$100),MONTH(Expenses!$A$2:$A$100),13)=4)*(Expenses!$D$2:$D$100="Other")) -> 0 | F14: =SUMPRODUCT((IF(ISNUMBER(Expenses!$G$2:$G$100),Expenses!$G$2:$G$100,0))*(IF(ISNUMBER(Expenses!$A$2:$A$100),MONTH(Expenses!$A$2:$A$100),13)=5)*(Expenses!$D$2:$D$100="Other")) -> 0 | G14: =SUMPRODUCT((IF(ISNUMBER(Expenses!$G$2:$G$100),Expenses!$G$2:$G$100,0))*(IF(ISNUMBER(Expenses!$A$2:$A$100),MONTH(Expenses!$A$2:$A$100),13)=6)*(Expenses!$D$2:$D$100="Other")) -> 0 | H14: =SUMPRODUCT((IF(ISNUMBER(Expenses!$G$2:$G$100),Expenses!$G$2:$G$100,0))*(IF(ISNUMBER(Expenses!$A$2:$A$100),MONTH(Expenses!$A$2:$A$100),13)=7)*(Expenses!$D$2:$D$100="Other")) -> 0 | I14: =SUMPRODUCT((IF(ISNUMBER(Expenses!$G$2:$G$100),Expenses!$G$2:$G$100,0))*(IF(ISNUMBER(Expenses!$A$2:$A$100),MONTH(Expenses!$A$2:$A$100),13)=8)*(Expenses!$D$2:$D$100="Other")) -> 0 | J14: =SUMPRODUCT((IF(ISNUMBER(Expenses!$G$2:$G$100),Expenses!$G$2:$G$100,0))*(IF(ISNUMBER(Expenses!$A$2:$A$100),MONTH(Expenses!$A$2:$A$100),13)=9)*(Expenses!$D$2:$D$100="Other")) -> 0 | K14: =SUMPRODUCT((IF(ISNUMBER(Expenses!$G$2:$G$100),Expenses!$G$2:$G$100,0))*(IF(ISNUMBER(Expenses!$A$2:$A$100),MONTH(Expenses!$A$2:$A$100),13)=10)*(Expenses!$D$2:$D$100="Other")) -> 0 | L14: =SUMPRODUCT((IF(ISNUMBER(Expenses!$G$2:$G$100),Expenses!$G$2:$G$100,0))*(IF(ISNUMBER(Expenses!$A$2:$A$100),MONTH(Expenses!$A$2:$A$100),13)=11)*(Expenses!$D$2:$D$100="Other")) -> 0 | M14: =SUMPRODUCT((IF(ISNUMBER(Expenses!$G$2:$G$100),Expenses!$G$2:$G$100,0))*(IF(ISNUMBER(Expenses!$A$2:$A$100),MONTH(Expenses!$A$2:$A$100),13)=12)*(Expenses!$D$2:$D$100="Other")) -> 0 | N14: =SUM(B14:M14) -> 0
A15: MONTHLY TOTAL | B15: =SUM(B5:B14) -> 0 | C15: =SUM(C5:C14) -> 0 | D15: =SUM(D5:D14) -> 483.78 | E15: =SUM(E5:E14) -> 1248.6 | F15: =SUM(F5:F14) -> 0 | G15: =SUM(G5:G14) -> 0 | H15: =SUM(H5:H14) -> 0 | I15: =SUM(I5:I14) -> 0 | ... M15: =SUM(M5:M14) -> 0 | N15: =SUM(B15:M15) -> 1732.38
A17: Quarterly Totals
A18: Quarter | B18: Ex VAT | C18: VAT | D18: Total
A19: Q1 | B19: =SUMPRODUCT((IF(ISNUMBER(Expenses!$E$2:$E$100),Expenses!$E$2:$E$100,0))*(IF(ISNUMBER(Expenses!$A$2:$A$100),MONTH(Expenses!$A$2:$A$100),13)>=1)*(IF(ISNUMBER(Expenses!$A$2:$A$100),MONTH(Expenses!$A$2:$A$100),13)<=3)) -> 407.32 | C19: =SUMPRODUCT((IF(ISNUMBER(Expenses!$F$2:$F$100),Expenses!$F$2:$F$100,0))*(IF(ISNUMBER(Expenses!$A$2:$A$100),MONTH(Expenses!$A$2:$A$100),13)>=1)*(IF(ISNUMBER(Expenses!$A$2:$A$100),MONTH(Expenses!$A$2:$A$100),13)<=3)) -> 76.46 | D19: =SUMPRODUCT((IF(ISNUMBER(Expenses!$G$2:$G$100),Expenses!$G$2:$G$100,0))*(IF(ISNUMBER(Expenses!$A$2:$A$100),MONTH(Expenses!$A$2:$A$100),13)>=1)*(IF(ISNUMBER(Expenses!$A$2:$A$100),MONTH(Expenses!$A$2:$A$100),13)<=3)) -> 483.78
A20: Q2 | B20: =SUMPRODUCT((IF(ISNUMBER(Expenses!$E$2:$E$100),Expenses!$E$2:$E$100,0))*(IF(ISNUMBER(Expenses!$A$2:$A$100),MONTH(Expenses!$A$2:$A$100),13)>=4)*(IF(ISNUMBER(Expenses!$A$2:$A$100),MONTH(Expenses!$A$2:$A$100),13)<=6)) -> 1168.45 | C20: =SUMPRODUCT((IF(ISNUMBER(Expenses!$F$2:$F$100),Expenses!$F$2:$F$100,0))*(IF(ISNUMBER(Expenses!$A$2:$A$100),MONTH(Expenses!$A$2:$A$100),13)>=4)*(IF(ISNUMBER(Expenses!$A$2:$A$100),MONTH(Expenses!$A$2:$A$100),13)<=6)) -> 80.15 | D20: =SUMPRODUCT((IF(ISNUMBER(Expenses!$G$2:$G$100),Expenses!$G$2:$G$100,0))*(IF(ISNUMBER(Expenses!$A$2:$A$100),MONTH(Expenses!$A$2:$A$100),13)>=4)*(IF(ISNUMBER(Expenses!$A$2:$A$100),MONTH(Expenses!$A$2:$A$100),13)<=6)) -> 1248.6
A21: Q3 | B21: =SUMPRODUCT((IF(ISNUMBER(Expenses!$E$2:$E$100),Expenses!$E$2:$E$100,0))*(IF(ISNUMBER(Expenses!$A$2:$A$100),MONTH(Expenses!$A$2:$A$100),13)>=7)*(IF(ISNUMBER(Expenses!$A$2:$A$100),MONTH(Expenses!$A$2:$A$100),13)<=9)) -> 0 | C21: =SUMPRODUCT((IF(ISNUMBER(Expenses!$F$2:$F$100),Expenses!$F$2:$F$100,0))*(IF(ISNUMBER(Expenses!$A$2:$A$100),MONTH(Expenses!$A$2:$A$100),13)>=7)*(IF(ISNUMBER(Expenses!$A$2:$A$100),MONTH(Expenses!$A$2:$A$100),13)<=9)) -> 0 | D21: =SUMPRODUCT((IF(ISNUMBER(Expenses!$G$2:$G$100),Expenses!$G$2:$G$100,0))*(IF(ISNUMBER(Expenses!$A$2:$A$100),MONTH(Expenses!$A$2:$A$100),13)>=7)*(IF(ISNUMBER(Expenses!$A$2:$A$100),MONTH(Expenses!$A$2:$A$100),13)<=9)) -> 0
A22: Q4 | B22: =SUMPRODUCT((IF(ISNUMBER(Expenses!$E$2:$E$100),Expenses!$E$2:$E$100,0))*(IF(ISNUMBER(Expenses!$A$2:$A$100),MONTH(Expenses!$A$2:$A$100),13)>=10)*(IF(ISNUMBER(Expenses!$A$2:$A$100),MONTH(Expenses!$A$2:$A$100),13)<=12)) -> 0 | C22: =SUMPRODUCT((IF(ISNUMBER(Expenses!$F$2:$F$100),Expenses!$F$2:$F$100,0))*(IF(ISNUMBER(Expenses!$A$2:$A$100),MONTH(Expenses!$A$2:$A$100),13)>=10)*(IF(ISNUMBER(Expenses!$A$2:$A$100),MONTH(Expenses!$A$2:$A$100),13)<=12)) -> 0 | D22: =SUMPRODUCT((IF(ISNUMBER(Expenses!$G$2:$G$100),Expenses!$G$2:$G$100,0))*(IF(ISNUMBER(Expenses!$A$2:$A$100),MONTH(Expenses!$A$2:$A$100),13)>=10)*(IF(ISNUMBER(Expenses!$A$2:$A$100),MONTH(Expenses!$A$2:$A$100),13)<=12)) -> 0
A25: Annual Totals
B26: Ex VAT | C26: VAT | D26: Total
A27: YTD 2026 | B27: =SUMPRODUCT(IF(ISNUMBER(Expenses!E2:E100),Expenses!E2:E100,0)) -> 3151.54 | C27: =SUM(Expenses!F2:F50) -> 152.61 | D27: =SUM(Expenses!G2:G50) -> 1708.38
A30: VAT Reclaimable (GBP receipts only)
A31: =SUMPRODUCT((IF(ISNUMBER(Expenses!$F$2:$F$100),Expenses!$F$2:$F$100,0))*(Expenses!$H$2:$H$100="GBP")) -> 114.48

Sheet Categories
A1: UK Business Expense Categories
A3: Category | B3: Description | C3: Example Vendors
A4: Software & SaaS | B4: Software subscriptions and cloud services | C4: Anthropic, Obsidian, Google Workspace, ElevenLabs, PostHog, Resend, fal.ai
A5: Advertising | B5: Paid advertising and marketing spend | C5: Google Ads, Meta/Facebook Ads, Awin
A6: Hosting & Infrastructure | B6: Web hosting, cloud servers, and deployment | C6: Vercel, Railway, Render, Supabase, Google Cloud
A7: Professional Services | B7: Legal, accounting, company formation | C7: 1st Formations, ICO, Accountants
A8: Office & Equipment | B8: Hardware, furniture, and office supplies
A9: Travel & Subsistence | B9: Business travel, meals, and accommodation
A10: Phone & Internet | B10: Business phone and broadband
A11: Bank Charges | B11: Banking fees and payment processing | C11: Stripe
A12: Insurance | B12: Business insurance premiums
A13: Domain Names | B13: Domain registration and renewal | C13: 123 Reg, GoDaddy, Namecheap
A14: Other | B14: Miscellaneous business expenses
